hippounit/__init__.py
hippounit/classify_apical_sections.py
hippounit/plottools.py
hippounit/utils.py
hippounit/capabilities/__init__.py
hippounit/capabilities/cap_InitialiseModel.py
hippounit/capabilities/cap_NumOfPossibleLocations.py
hippounit/capabilities/cap_ProvidesGoodObliques.py
hippounit/capabilities/cap_ProvidesRandomDendriticLocations.py
hippounit/capabilities/cap_ProvidesRecordingLocationsOnTrunk.py
hippounit/capabilities/cap_ReceivesCurrentStimuli_ProvidesResponse.py
hippounit/capabilities/cap_ReceivesCurrentStimuli_ProvidesResponse_MultipleLocations.py
hippounit/capabilities/cap_ReceivesEPSCstim.py
hippounit/capabilities/cap_ReceivesMultipleSquareCurrents.py
hippounit/capabilities/cap_ReceivesMultipleSynapses.py
hippounit/capabilities/cap_ReceivesSynapse.py
hippounit/capabilities/cap_ReceivesSynapseGivenPathway.py
hippounit/capabilities/cap_RunSimulation_ReturnTraces.py
hippounit/capabilities/cap_ThetaSynapticStimuli.py
hippounit/scores/__init__.py
hippounit/scores/score_P_Value_ObliqueIntegration.py
hippounit/scores/score_ZScore_ObliqueIntegration.py
hippounit/scores/score_ZScore_PSPAttenuation.py
hippounit/scores/score_ZScore_PathwayInteraction.py
hippounit/scores/score_ZScore_backpropagatingAP.py
hippounit/scores/score_ZScore_depolblock.py
hippounit/scores/score_ZScore_somaticSpiking.py
hippounit/tests/__init__.py
hippounit/tests/test_BackpropagatingAPTest.py
hippounit/tests/test_DepolarizationBlockTest.py
hippounit/tests/test_ObliqueIntegrationTest.py
hippounit/tests/test_PSPAttenuationTest.py
hippounit/tests/test_PathwayInteraction.py
hippounit/tests/test_SomaticFeaturesTest.py
hippounit/tests/default_NMDAr/NMDA_CA1_pyr_SC.mod
hippounit/tests/stimuli/PSP_attenuation_stim/stim_PSP_attenuation_test.json
hippounit/tests/stimuli/PathwayInteraction_stim/stim_PathwayInteraction_test.json
hippounit/tests/stimuli/bAP_stim/stim_bAP_test.json
hippounit/tests/stimuli/somafeat_stim/stim_CA1_int_bAC.json
hippounit-1.4.1.dist-info/LICENSE.txt
hippounit-1.4.1.dist-info/METADATA
hippounit-1.4.1.dist-info/WHEEL
hippounit-1.4.1.dist-info/top_level.txt
hippounit-1.4.1.dist-info/RECORD
