Metadata-Version: 2.1
Name: hippounit
Version: 1.4.1
Summary: A SciUnit library for data-driven validation testing of models of hippocampus.
Home-page: http://github.com/kalilab/hippounit
Author: Sara Saray, Szabolcs Kali, Christian Rossert, Andrew Davison, Shailesh Appukuttan
Author-email: saray.sara@koki.hu, kali@koki.hu, christian.rossert@epfl.ch, andrew.davison@unic.cnrs-gif.fr, shailesh.appukuttan@unic.cnrs-gif.fr
License: MIT
Platform: UNKNOWN
Requires-Dist: efel
Requires-Dist: sciunit (>=0.2.1)
